segment_plugin-0.2.8.dist-info/METADATA
segment_plugin-0.2.8.dist-info/WHEEL
segment_plugin-0.2.8.dist-info/licenses/LICENSE
segment_plugin/__init__.py
segment_plugin/_internal.cpython-313-darwin.so
segment_plugin/funcs.py
segment_plugin/pandas/__init__.py
segment_plugin/segment.py
segment_plugin/segment_pd.py
segment_plugin/typing.py
segment_plugin-0.2.8.dist-info/RECORD
