Metadata-Version: 2.4
Name: segment-plugin
Version: 0.2.8
Classifier: Programming Language :: Rust
Classifier: Programming Language :: Python :: Implementation :: CPython
Classifier: Programming Language :: Python :: Implementation :: PyPy
Requires-Dist: polars>=1.31.0
Requires-Dist: scipy>=1.16.0
Requires-Dist: tqdm>=4.67.1
Requires-Dist: pandas>=2.2.3 ; extra == 'pandas'
Provides-Extra: pandas
License-File: LICENSE
Author: Ethan Hershey
License: MIT
Requires-Python: >=3.8
